[
 {
  "@module": "pymatgen.entries.computed_entries",
  "@class": "ComputedStructureEntry",
  "energy": -18.54877822,
  "composition": {
   "Ru": 2.0
  },
  "entry_id": "mp-33",
  "correction": 0.0,
  "energy_adjustments": [],
  "parameters": {
   "run_type": "GGA",
   "is_hubbard": false,
   "pseudo_potential": {
    "functional": "PBE",
    "labels": [
     "Ru_pv"
    ],
    "pot_type": "paw"
   },
   "hubbards": {},
   "potcar_symbols": [
    "PBE Ru_pv"
   ],
   "oxide_type": "None"
  },
  "data": {
   "oxide_type": "None",
   "ML_eads": {
    "2-13": {
     "N": {
      "eads": -0.6242395639419556,
      "sid": "13"
     },
     "O": {
      "eads": -0.5982452630996704,
      "sid": "6"
     }
    },
    "323": {
     "N": {
      "eads": -0.861623227596283,
      "sid": "45"
     },
     "O": {
      "eads": -0.8147457838058472,
      "sid": "30"
     }
    },
    "302": {
     "N": {
      "eads": -0.8404085636138916,
      "sid": "79"
     },
     "O": {
      "eads": -0.37004637718200684,
      "sid": "82"
     }
    },
    "321": {
     "N": {
      "eads": -0.798244833946228,
      "sid": "151"
     },
     "O": {
      "eads": -0.708084762096405,
      "sid": "138"
     }
    },
    "3-13": {
     "N": {
      "eads": -0.9409531354904175,
      "sid": "193"
     },
     "O": {
      "eads": -0.7395794987678528,
      "sid": "176"
     }
    },
    "2-12": {
     "N": {
      "eads": -0.48384737968444824,
      "sid": "225"
     },
     "O": {
      "eads": -0.59400874376297,
      "sid": "224"
     }
    }
   },
   "activity_selectivity": {
    "0": {
     "excellent": {
      "2-13": [
       0.4460456858235482,
       true,
       false
      ],
      "323": [
       0.5576545360347627,
       true,
       false
      ],
      "302": [
       0.13786486131246758,
       true,
       false
      ],
      "321": [
       0.48078276122958724,
       true,
       false
      ],
      "3-13": [
       0.4528230823257805,
       true,
       false
      ],
      "2-12": [
       0.49932173170899924,
       true,
       false
      ]
     },
     "good": {
      "2-13": [
       0.4556849088874175,
       true,
       false
      ],
      "323": [
       0.5665147980810832,
       true,
       false
      ],
      "302": [
       0.1472474014900156,
       true,
       false
      ],
      "321": [
       0.4899029912859438,
       true,
       false
      ],
      "3-13": [
       0.4615800174485153,
       true,
       false
      ],
      "2-12": [
       0.509289888995522,
       true,
       false
      ]
     }
    },
    "0.1": {
     "excellent": {
      "2-13": [
       0.7319380931793608,
       true,
       false
      ],
      "323": [
       1.0289293474748762,
       true,
       false
      ],
      "302": [
       0.5711781581676267,
       true,
       false
      ],
      "321": [
       0.9066947051323494,
       true,
       false
      ],
      "3-13": [
       0.9725940948741256,
       true,
       false
      ],
      "2-12": [
       0.7816145280919551,
       true,
       false
      ]
     },
     "good": {
      "2-13": [
       0.8564402666740506,
       true,
       false
      ],
      "323": [
       0.9776807876926285,
       true,
       false
      ],
      "302": [
       0.5516130442087913,
       true,
       false
      ],
      "321": [
       0.8976152195527513,
       true,
       false
      ],
      "3-13": [
       0.8741892966843268,
       true,
       false
      ],
      "2-12": [
       0.905596790573268,
       true,
       false
      ]
     }
    },
    "0.2": {
     "excellent": {
      "2-13": [
       1.084835746042868,
       true,
       false
      ],
      "323": [
       1.3070326370538015,
       true,
       false
      ],
      "302": [
       0.7792945510656341,
       true,
       false
      ],
      "321": [
       1.1246894680002715,
       true,
       false
      ],
      "3-13": [
       1.2312456108897891,
       true,
       false
      ],
      "2-12": [
       1.134843662039159,
       true,
       false
      ]
     },
     "good": {
      "2-13": [
       1.1635846728927395,
       true,
       false
      ],
      "323": [
       1.2751661621105346,
       true,
       false
      ],
      "302": [
       0.8553947959469156,
       true,
       false
      ],
      "321": [
       1.1983035144904743,
       true,
       false
      ],
      "3-13": [
       1.1703310664028141,
       true,
       false
      ],
      "2-12": [
       1.2168722831976047,
       true,
       false
      ]
     }
    }
   },
   "energy_above_hull": 0
  },
  "structure": {
   "@module": "pymatgen.core.structure",
   "@class": "Structure",
   "charge": null,
   "lattice": {
    "matrix": [
     [
      1.3664650418366904,
      -2.3667868792278792,
      0.0
     ],
     [
      1.3664650418366904,
      2.3667868792278792,
      0.0
     ],
     [
      0.0,
      0.0,
      4.313923
     ]
    ],
    "a": 2.7329300836733808,
    "b": 2.7329300836733808,
    "c": 4.313923,
    "alpha": 90.0,
    "beta": 90.0,
    "gamma": 120.00000000000001,
    "volume": 27.9035888013453
   },
   "sites": [
    {
     "species": [
      {
       "element": "Ru",
       "occu": 1
      }
     ],
     "abc": [
      0.6666666666666666,
      0.3333333333333333,
      0.25
     ],
     "xyz": [
      1.3664650418366904,
      -0.7889289597426263,
      1.07848075
     ],
     "label": "Ru",
     "properties": {}
    },
    {
     "species": [
      {
       "element": "Ru",
       "occu": 1
      }
     ],
     "abc": [
      0.33333333333333337,
      0.6666666666666667,
      0.75
     ],
     "xyz": [
      1.3664650418366906,
      0.7889289597426264,
      3.23544225
     ],
     "label": "Ru",
     "properties": {}
    }
   ]
  }
 }
]